pushould
