Metadata-Version: 1.0
Name: pushould-python
Version: 0.0.3
Summary: RealTime without pain.
Home-page: https://pushould.com
Author: Yu Hoshino
Author-email: yhoshino11@gmail.com
License: MIT
Platform: UNKNOWN
